bioconda2biocontainer/__init__.py
bioconda2biocontainer/biocontainer.py
bioconda2biocontainer/entry_point.py
bioconda2biocontainer/entry_point_search.py
bioconda2biocontainer/entry_point_update_cwl_docker.py
bioconda2biocontainer/update_cwl_docker_image.py
bioconda2biocontainer-0.0.7.data/data/README.md
bioconda2biocontainer-0.0.7.dist-info/LICENSE
bioconda2biocontainer-0.0.7.dist-info/METADATA
bioconda2biocontainer-0.0.7.dist-info/WHEEL
bioconda2biocontainer-0.0.7.dist-info/entry_points.txt
bioconda2biocontainer-0.0.7.dist-info/top_level.txt
bioconda2biocontainer-0.0.7.dist-info/RECORD
