Metadata-Version: 2.1
Name: bioconda2biocontainer
Version: 0.0.7
Summary: Tools to synchronize bioconda packages and versions with Biocontainer images
Home-page: https://github.com/BioContainers/bioconda2biocontainer
Author: Vera Alvarez, Roberto
Author-email: veraalva@ncbi.nlm.nih.gov
Maintainer: Vera Alvarez, Roberto
Maintainer-email: veraalva@ncbi.nlm.nih.gov
License: Public Domain
Project-URL: Documentation, https://github.com/BioContainers/bioconda2biocontainer/issues
Project-URL: Source, https://github.com/BioContainers/bioconda2biocontainer
Project-URL: Tracker, https://github.com/BioContainers/bioconda2biocontainer/issues
Keywords: Biocontainers
Classifier: Development Status :: 3 - Alpha
Classifier: Intended Audience :: Science/Research
Classifier: License :: Public Domain
Classifier: Natural Language :: English
Classifier: Operating System :: Unix
Classifier: Programming Language :: Python :: 3
Classifier: Programming Language :: Python :: 3.7
Classifier: Programming Language :: Python :: 3.8
Classifier: Programming Language :: Python :: 3.9
Classifier: Topic :: Scientific/Engineering :: Bio-Informatics
License-File: LICENSE
Requires-Dist: requests
Requires-Dist: PyYAML
